{"cameraMode":{"drawMode":0,"name":"Shaded","section":"Shading Mode"},"sceneLighting":false,"audioPlay":false,"sceneViewState":{"m_AlwaysRefresh":false,"showFog":true,"showSkybox":false,"showFlares":true,"showImageEffects":true,"showParticleSystems":true,"showVisualEffectGraphs":true,"m_FxEnabled":true},"in2DMode":false,"pivot":{"x":7.41133975982666,"y":-2.1552510261535646,"z":-79.34601593017578},"rotation":{"x":0.07574843615293503,"y":0.6786328554153442,"z":-0.0706910490989685,"w":0.7271385192871094},"size":6.189693927764893,"orthographic":false}